README.txt
setup.py
docs/HISTORY.txt
zopyx/__init__.py
zopyx.parallel_svn_externals_updater.egg-info/PKG-INFO
zopyx.parallel_svn_externals_updater.egg-info/SOURCES.txt
zopyx.parallel_svn_externals_updater.egg-info/dependency_links.txt
zopyx.parallel_svn_externals_updater.egg-info/entry_points.txt
zopyx.parallel_svn_externals_updater.egg-info/namespace_packages.txt
zopyx.parallel_svn_externals_updater.egg-info/not-zip-safe
zopyx.parallel_svn_externals_updater.egg-info/requires.txt
zopyx.parallel_svn_externals_updater.egg-info/top_level.txt
zopyx/parallel_svn_externals_updater/__init__.py
zopyx/parallel_svn_externals_updater/cli.py
zopyx/parallel_svn_externals_updater/test.py
zopyx/parallel_svn_externals_updater/xx.py