Metadata-Version: 1.0
Name: zopyx.parallel-svn-externals-updater
Version: 0.1.0
Summary: Script for parallel update of  svn:externals within a SVN checkout
Home-page: http://svn.plone.org/svn/collective/zopyx.parallel_svn_externals_updater
Author: Andreas Jung
Author-email: info@zopyx.com
License: ZPL
Keywords: Subversion SVN externals
Platform: UNKNOWN
Classifier: Programming Language :: Python
Classifier: Topic :: Software Development :: Libraries :: Python Modules
